metcli/__init__.py
metcli/command_line.py
metcli/loader.py
metcli/metcli.py
metcli/test_metcli.py
metcli-0.1.1.dist-info/LICENSE.md
metcli-0.1.1.dist-info/METADATA
metcli-0.1.1.dist-info/WHEEL
metcli-0.1.1.dist-info/entry_points.txt
metcli-0.1.1.dist-info/top_level.txt
metcli-0.1.1.dist-info/RECORD
