Metadata-Version: 2.1
Name: metcli
Version: 0.1.1
Summary: A command line interface for Met Éireann.
Home-page: https://github.com/ozzywalsh/metcli
Author: Ozzy Walsh
License: MIT
Keywords: weather utility cli
Platform: UNKNOWN
Classifier: License :: OSI Approved :: MIT License
Classifier: Programming Language :: Python :: 3.8
Classifier: Topic :: Utilities
Requires-Dist: requests
Requires-Dist: termcolor
